numba_linalg/_API.py
numba_linalg/__init__.py
numba_linalg-0.0.1.dist-info/LICENSE.txt
numba_linalg-0.0.1.dist-info/METADATA
numba_linalg-0.0.1.dist-info/WHEEL
numba_linalg-0.0.1.dist-info/top_level.txt
numba_linalg-0.0.1.dist-info/RECORD
